{
    "title": "Section Navigation",
    "slug" : "section-nav",
    "fullname": "il-section-nav",
    "environment" : "",
    "status": "Custom Element; v2.0.0; 7/12/2021",
    "sample": " <h3> <a href=\"#\">Programs of Study</a> </h3> <ul> <li> <a href=\"#\">Undergraduate Degrees</a> <ul> <li> <a href=\"#\">Animal Sciences Major</a> <ul> <li> <a href=\"#\" id=\"link\">Companion Animal Equine Science Active Page</a> </li> <li> <a href=\"#\">Food Animal Production and Management</a> </li> <li> <a href=\"#\">Science, Pre-Veterinary, and Medical</a> </li> </ul> </li> <li> <a href=\"#\">Computer Science &amp; Animal Science</a> </li> <li> <a href=\"#\">Some Third Thing</a> </li> </ul> </li> </ul> "
}